hello_world/__init__.py
adipypi_hello_world-0.1.0.dist-info/METADATA
adipypi_hello_world-0.1.0.dist-info/WHEEL
adipypi_hello_world-0.1.0.dist-info/top_level.txt
adipypi_hello_world-0.1.0.dist-info/RECORD
